footballbrainz_data_models/__init__.py
footballbrainz_data_models/models/__init__.py
footballbrainz_data_models/models/attribute_definition.py
footballbrainz_data_models/models/attribute_projection.py
footballbrainz_data_models/models/bet.py
footballbrainz_data_models/models/db_index.py
footballbrainz_data_models/models/game.py
footballbrainz_data_models/models/league.py
footballbrainz_data_models/models/primary_key.py
footballbrainz_data_models/models/team.py
footballbrainz_data_models-0.0.9.dist-info/METADATA
footballbrainz_data_models-0.0.9.dist-info/WHEEL
footballbrainz_data_models-0.0.9.dist-info/top_level.txt
footballbrainz_data_models-0.0.9.dist-info/RECORD
